{
  "metadata": {
    "source": "intelligent_name_mapping",
    "date": "2025-11-09",
    "method": "fuzzy_similarity + keyword_overlap",
    "threshold": 0.5
  },
  "aws_mappings": [
    {
      "rule_list_id": "aws.ec2.instance.user_data_no_secrets",
      "compliance_function": "aws_ec2_instance_secrets_user_data",
      "similarity_score": 0.859,
      "match_type": "similarity",
      "rule_details": {
        "cloud_provider": "aws",
        "service": "ec2",
        "resource": "instance",
        "program": "compute.security.vm.user_data_no_secrets",
        "scope": "compute.vm",
        "implementation_status": "stub"
      },
      "compliance_usage": 3
    },
    {
      "rule_list_id": "aws.ec2.launch_template.no_public_ip_default",
      "compliance_function": "aws_ec2_launch_template_no_public_ip",
      "similarity_score": 0.83,
      "match_type": "similarity",
      "rule_details": {
        "cloud_provider": "aws",
        "service": "ec2",
        "resource": "launch_template",
        "program": "compute.security.launch_template.no_public_ip_default",
        "scope": "compute.launch_template",
        "implementation_status": "stub"
      },
      "compliance_usage": 4
    },
    {
      "rule_list_id": "aws.ec2.instance.no_public_ip_assigned",
      "compliance_function": "aws_ec2_instance_no_public_ip",
      "similarity_score": 0.79,
      "match_type": "similarity",
      "rule_details": {
        "cloud_provider": "aws",
        "service": "ec2",
        "resource": "instance",
        "program": "compute.security.vm.no_public_ip_assigned",
        "scope": "compute.vm",
        "implementation_status": "stub"
      },
      "compliance_usage": 87
    },
    {
      "rule_list_id": "aws.ebs.volume.snapshots_encrypted",
      "compliance_function": "aws_ec2_ebs_snapshots_encrypted",
      "similarity_score": 0.788,
      "match_type": "similarity",
      "rule_details": {
        "cloud_provider": "aws",
        "service": "ebs",
        "resource": "volume",
        "program": "data_protection_storage.security.volume.snapshots_encrypted",
        "scope": "storage.volume",
        "implementation_status": "stub"
      },
      "compliance_usage": 2
    },
    {
      "rule_list_id": "aws.ebs.snapshot.snapshots_encrypted",
      "compliance_function": "aws_ec2_ebs_snapshots_encrypted",
      "similarity_score": 0.779,
      "match_type": "similarity",
      "rule_details": {
        "cloud_provider": "aws",
        "service": "ebs",
        "resource": "snapshot",
        "program": "compute.security.disk.snapshots_encrypted",
        "scope": "compute.disk",
        "implementation_status": "stub"
      },
      "compliance_usage": 2
    },
    {
      "rule_list_id": "aws.backup.backup_vault.encryption_at_rest_enabled",
      "compliance_function": "aws_backup_vault_encryption_enabled",
      "similarity_score": 0.77,
      "match_type": "similarity",
      "rule_details": {
        "cloud_provider": "aws",
        "service": "backup",
        "resource": "backup_vault",
        "program": "backup.security.encryption.encryption_at_rest_enabled",
        "scope": "backup.vault",
        "implementation_status": "stub"
      },
      "compliance_usage": 1
    },
    {
      "rule_list_id": "aws.ec2.launch_template.user_data_no_secrets",
      "compliance_function": "aws_ec2_launch_template_no_secrets",
      "similarity_score": 0.757,
      "match_type": "similarity",
      "rule_details": {
        "cloud_provider": "aws",
        "service": "ec2",
        "resource": "launch_template",
        "program": "compute.security.launch_template.user_data_no_secrets",
        "scope": "compute.launch_template",
        "implementation_status": "stub"
      },
      "compliance_usage": 3
    },
    {
      "rule_list_id": "aws.s3.bucket.encryption_at_rest_enabled",
      "compliance_function": "aws_efs_encryption_at_rest_enabled",
      "similarity_score": 0.753,
      "match_type": "similarity",
      "rule_details": {
        "cloud_provider": "aws",
        "service": "s3",
        "resource": "bucket",
        "program": "data_protection_storage.security.bucket.encryption_at_rest_enabled",
        "scope": "storage.bucket",
        "implementation_status": "stub"
      },
      "compliance_usage": 33
    },
    {
      "rule_list_id": "aws.api_gatewayv2.stage.api_access_logging_enabled",
      "compliance_function": "aws_apigatewayv2_api_access_logging_enabled",
      "similarity_score": 0.743,
      "match_type": "similarity",
      "rule_details": {
        "cloud_provider": "aws",
        "service": "api_gatewayv2",
        "resource": "stage",
        "program": "api_security.monitoring.api_access_logging_enabled",
        "scope": "api.monitoring",
        "implementation_status": "stub"
      },
      "compliance_usage": 3
    },
    {
      "rule_list_id": "aws.api_gateway.stage.api_access_logging_enabled",
      "compliance_function": "aws_apigatewayv2_api_access_logging_enabled",
      "similarity_score": 0.731,
      "match_type": "similarity",
      "rule_details": {
        "cloud_provider": "aws",
        "service": "api_gateway",
        "resource": "stage",
        "program": "api_security.monitoring.api_access_logging_enabled",
        "scope": "api.monitoring",
        "implementation_status": "stub"
      },
      "compliance_usage": 3
    },
    {
      "rule_list_id": "aws.ec2.instance.vtpm_enabled",
      "compliance_function": "aws_ec2_instance_imdsv2_enabled",
      "similarity_score": 0.723,
      "match_type": "similarity",
      "rule_details": {
        "cloud_provider": "aws",
        "service": "ec2",
        "resource": "instance",
        "program": "compute.security.vm.vtpm_enabled",
        "scope": "compute.vm",
        "implementation_status": "stub"
      },
      "compliance_usage": 45
    },
    {
      "rule_list_id": "aws.ec2.launch_template.imds_hardened",
      "compliance_function": "aws_ec2_launch_template_imdsv2_required",
      "similarity_score": 0.716,
      "match_type": "similarity",
      "rule_details": {
        "cloud_provider": "aws",
        "service": "ec2",
        "resource": "launch_template",
        "program": "compute.security.launch_template.imds_hardened",
        "scope": "compute.launch_template",
        "implementation_status": "stub"
      },
      "compliance_usage": 3
    },
    {
      "rule_list_id": "aws.ebs.volume.encryption_at_rest_enabled",
      "compliance_function": "aws_efs_encryption_at_rest_enabled",
      "similarity_score": 0.672,
      "match_type": "similarity",
      "rule_details": {
        "cloud_provider": "aws",
        "service": "ebs",
        "resource": "volume",
        "program": "data_protection_storage.security.volume.encryption_at_rest_enabled",
        "scope": "storage.volume",
        "implementation_status": "stub"
      },
      "compliance_usage": 33
    },
    {
      "rule_list_id": "aws.ebs.volume.snapshots_not_public",
      "compliance_function": "aws_ec2_ebs_volume_snapshots_exists",
      "similarity_score": 0.663,
      "match_type": "similarity",
      "rule_details": {
        "cloud_provider": "aws",
        "service": "ebs",
        "resource": "volume",
        "program": "compute.security.disk.snapshots_not_public",
        "scope": "compute.disk",
        "implementation_status": "stub"
      },
      "compliance_usage": 1
    },
    {
      "rule_list_id": "aws.ebs.snapshot.encryption_at_rest_enabled",
      "compliance_function": "aws_efs_encryption_at_rest_enabled",
      "similarity_score": 0.662,
      "match_type": "similarity",
      "rule_details": {
        "cloud_provider": "aws",
        "service": "ebs",
        "resource": "snapshot",
        "program": "compute.security.disk.encryption_at_rest_enabled",
        "scope": "compute.disk",
        "implementation_status": "stub"
      },
      "compliance_usage": 33
    },
    {
      "rule_list_id": "aws.ebs.volume.cmk_cmek_configured",
      "compliance_function": "aws_ebs_volume_backup_configured",
      "similarity_score": 0.655,
      "match_type": "similarity",
      "rule_details": {
        "cloud_provider": "aws",
        "service": "ebs",
        "resource": "volume",
        "program": "data_protection_storage.security.volume.cmk_cmek_configured",
        "scope": "storage.volume",
        "implementation_status": "stub"
      },
      "compliance_usage": 1
    },
    {
      "rule_list_id": "aws.cloudwatch.metric.api_access_logging_enabled",
      "compliance_function": "aws_apigatewayv2_api_access_logging_enabled",
      "similarity_score": 0.645,
      "match_type": "similarity",
      "rule_details": {
        "cloud_provider": "aws",
        "service": "cloudwatch",
        "resource": "metric",
        "program": "api_security.monitoring.api_access_logging_enabled",
        "scope": "api.monitoring",
        "implementation_status": "stub"
      },
      "compliance_usage": 3
    },
    {
      "rule_list_id": "aws.ec2.instance.ssh_key_based_auth_required",
      "compliance_function": "aws_ec2_instance_ssh_key_authentication",
      "similarity_score": 0.645,
      "match_type": "similarity",
      "rule_details": {
        "cloud_provider": "aws",
        "service": "ec2",
        "resource": "instance",
        "program": "compute.security.vm.ssh_key_based_auth_required",
        "scope": "compute.vm",
        "implementation_status": "stub"
      },
      "compliance_usage": 1
    },
    {
      "rule_list_id": "aws.glacier.vault.encryption_at_rest_enabled",
      "compliance_function": "aws_efs_encryption_at_rest_enabled",
      "similarity_score": 0.644,
      "match_type": "similarity",
      "rule_details": {
        "cloud_provider": "aws",
        "service": "glacier",
        "resource": "vault",
        "program": "backup.security.encryption.encryption_at_rest_enabled",
        "scope": "backup.vault",
        "implementation_status": "stub"
      },
      "compliance_usage": 33
    },
    {
      "rule_list_id": "aws.ec2.instance.imds_hardened",
      "compliance_function": "aws_ec2_instance_imdsv2_enabled",
      "similarity_score": 0.632,
      "match_type": "similarity",
      "rule_details": {
        "cloud_provider": "aws",
        "service": "ec2",
        "resource": "instance",
        "program": "compute.security.vm.imds_hardened",
        "scope": "compute.vm",
        "implementation_status": "stub"
      },
      "compliance_usage": 45
    },
    {
      "rule_list_id": "aws.backup.backup_vault.key_rotation_enabled",
      "compliance_function": "aws_backup_vault_encryption_enabled",
      "similarity_score": 0.627,
      "match_type": "similarity",
      "rule_details": {
        "cloud_provider": "aws",
        "service": "backup",
        "resource": "backup_vault",
        "program": "backup.security.encryption.key_rotation_enabled",
        "scope": "backup.vault",
        "implementation_status": "stub"
      },
      "compliance_usage": 1
    },
    {
      "rule_list_id": "aws.ec2.instance.security_group_inbound_restricted",
      "compliance_function": "aws_ec2_security_group_cifs_unrestricted_access_check",
      "similarity_score": 0.623,
      "match_type": "similarity",
      "rule_details": {
        "cloud_provider": "aws",
        "service": "ec2",
        "resource": "instance",
        "program": "compute.security.vm.security_group_inbound_restricted",
        "scope": "compute.vm",
        "implementation_status": "stub"
      },
      "compliance_usage": 1
    },
    {
      "rule_list_id": "aws.ec2.instance.root_volume_encrypted_cmek",
      "compliance_function": "aws_ec2_ebs_volume_encrypted",
      "similarity_score": 0.613,
      "match_type": "similarity",
      "rule_details": {
        "cloud_provider": "aws",
        "service": "ec2",
        "resource": "instance",
        "program": "compute.security.vm.root_volume_encrypted_cmek",
        "scope": "compute.vm",
        "implementation_status": "stub"
      },
      "compliance_usage": 3
    },
    {
      "rule_list_id": "aws.cloudwatch.metric.api_access_log_sink_configured",
      "compliance_function": "aws_cloudwatch_log_metric_filter_alarm_configured",
      "similarity_score": 0.608,
      "match_type": "similarity",
      "rule_details": {
        "cloud_provider": "aws",
        "service": "cloudwatch",
        "resource": "metric",
        "program": "api_security.monitoring.api_access_log_sink_configured",
        "scope": "api.monitoring",
        "implementation_status": "stub"
      },
      "compliance_usage": 2
    },
    {
      "rule_list_id": "aws.ec2.ami.encrypted_cmek",
      "compliance_function": "aws_ec2_ebs_volume_encrypted",
      "similarity_score": 0.597,
      "match_type": "similarity",
      "rule_details": {
        "cloud_provider": "aws",
        "service": "ec2",
        "resource": "ami",
        "program": "compute.security.image.encrypted_cmek",
        "scope": "compute.image",
        "implementation_status": "stub"
      },
      "compliance_usage": 3
    },
    {
      "rule_list_id": "aws.ec2.launch_template.security_groups_restrictive",
      "compliance_function": "aws_ec2_launch_template_no_secrets",
      "similarity_score": 0.597,
      "match_type": "similarity",
      "rule_details": {
        "cloud_provider": "aws",
        "service": "ec2",
        "resource": "launch_template",
        "program": "compute.security.launch_template.security_groups_restrictive",
        "scope": "compute.launch_template",
        "implementation_status": "stub"
      },
      "compliance_usage": 3
    },
    {
      "rule_list_id": "aws.ec2.instance.secure_boot_enabled",
      "compliance_function": "aws_ec2_instance_profile_attached",
      "similarity_score": 0.596,
      "match_type": "similarity",
      "rule_details": {
        "cloud_provider": "aws",
        "service": "ec2",
        "resource": "instance",
        "program": "compute.security.vm.secure_boot_enabled",
        "scope": "compute.vm",
        "implementation_status": "stub"
      },
      "compliance_usage": 20
    },
    {
      "rule_list_id": "aws.ec2.instance.ssh_password_auth_disabled",
      "compliance_function": "aws_ec2_instance_ssh_key_authentication",
      "similarity_score": 0.587,
      "match_type": "similarity",
      "rule_details": {
        "cloud_provider": "aws",
        "service": "ec2",
        "resource": "instance",
        "program": "compute.security.vm.ssh_password_auth_disabled",
        "scope": "compute.vm",
        "implementation_status": "stub"
      },
      "compliance_usage": 1
    },
    {
      "rule_list_id": "aws.s3.bucket.key_rotation_enabled",
      "compliance_function": "aws_s3_bucket_replication_enabled",
      "similarity_score": 0.582,
      "match_type": "similarity",
      "rule_details": {
        "cloud_provider": "aws",
        "service": "s3",
        "resource": "bucket",
        "program": "backup.security.encryption.key_rotation_enabled",
        "scope": "backup.vault",
        "implementation_status": "stub"
      },
      "compliance_usage": 11
    },
    {
      "rule_list_id": "aws.backup.backup_vault.encryption_in_transit_tls_min_1_2",
      "compliance_function": "aws_backup_vault_encryption_enabled",
      "similarity_score": 0.581,
      "match_type": "similarity",
      "rule_details": {
        "cloud_provider": "aws",
        "service": "backup",
        "resource": "backup_vault",
        "program": "backup.security.encryption.encryption_in_transit_tls_min_1_2",
        "scope": "backup.vault",
        "implementation_status": "stub"
      },
      "compliance_usage": 1
    },
    {
      "rule_list_id": "aws.ebs.snapshot.snapshots_not_public",
      "compliance_function": "aws_ec2_ebs_public_snapshot",
      "similarity_score": 0.575,
      "match_type": "similarity",
      "rule_details": {
        "cloud_provider": "aws",
        "service": "ebs",
        "resource": "snapshot",
        "program": "compute.security.disk.snapshots_not_public",
        "scope": "compute.disk",
        "implementation_status": "stub"
      },
      "compliance_usage": 91
    },
    {
      "rule_list_id": "aws.ec2.ami.not_publicly_shared",
      "compliance_function": "aws_ec2_ami_public",
      "similarity_score": 0.561,
      "match_type": "similarity",
      "rule_details": {
        "cloud_provider": "aws",
        "service": "ec2",
        "resource": "ami",
        "program": "compute.security.image.not_publicly_shared",
        "scope": "compute.image",
        "implementation_status": "stub"
      },
      "compliance_usage": 3
    },
    {
      "rule_list_id": "aws.glacier.vault.key_policy_least_privilege",
      "compliance_function": "aws_iam_qldb_access_policy_least_privilege_audit",
      "similarity_score": 0.561,
      "match_type": "similarity",
      "rule_details": {
        "cloud_provider": "aws",
        "service": "glacier",
        "resource": "vault",
        "program": "backup.security.encryption.key_policy_least_privilege",
        "scope": "backup.vault",
        "implementation_status": "stub"
      },
      "compliance_usage": 1
    },
    {
      "rule_list_id": "aws.s3.bucket.key_policy_least_privilege",
      "compliance_function": "aws_iam_role_least_privilege",
      "similarity_score": 0.559,
      "match_type": "similarity",
      "rule_details": {
        "cloud_provider": "aws",
        "service": "s3",
        "resource": "bucket",
        "program": "backup.security.encryption.key_policy_least_privilege",
        "scope": "backup.vault",
        "implementation_status": "stub"
      },
      "compliance_usage": 2
    },
    {
      "rule_list_id": "aws.backup.backup_vault.backup_storage_immutability_enabled",
      "compliance_function": "aws_backup_vault_encryption_enabled",
      "similarity_score": 0.555,
      "match_type": "similarity",
      "rule_details": {
        "cloud_provider": "aws",
        "service": "backup",
        "resource": "backup_vault",
        "program": "backup.security.encryption.backup_storage_immutability_enabled",
        "scope": "backup.vault",
        "implementation_status": "stub"
      },
      "compliance_usage": 1
    },
    {
      "rule_list_id": "aws.backup.backup_vault.key_policy_least_privilege",
      "compliance_function": "aws_iam_qldb_access_policy_least_privilege_audit",
      "similarity_score": 0.553,
      "match_type": "similarity",
      "rule_details": {
        "cloud_provider": "aws",
        "service": "backup",
        "resource": "backup_vault",
        "program": "backup.security.encryption.key_policy_least_privilege",
        "scope": "backup.vault",
        "implementation_status": "stub"
      },
      "compliance_usage": 1
    },
    {
      "rule_list_id": "aws.api_gatewayv2.stage.api_access_log_sink_configured",
      "compliance_function": "aws_apigatewayv2_api_access_logging_enabled",
      "similarity_score": 0.543,
      "match_type": "similarity",
      "rule_details": {
        "cloud_provider": "aws",
        "service": "api_gatewayv2",
        "resource": "stage",
        "program": "api_security.monitoring.api_access_log_sink_configured",
        "scope": "api.monitoring",
        "implementation_status": "stub"
      },
      "compliance_usage": 3
    },
    {
      "rule_list_id": "aws.s3.bucket.encryption_in_transit_tls_min_1_2",
      "compliance_function": "aws_docdb_cluster_encryption_in_transit_enabled",
      "similarity_score": 0.542,
      "match_type": "similarity",
      "rule_details": {
        "cloud_provider": "aws",
        "service": "s3",
        "resource": "bucket",
        "program": "backup.security.encryption.encryption_in_transit_tls_min_1_2",
        "scope": "backup.vault",
        "implementation_status": "stub"
      },
      "compliance_usage": 1
    },
    {
      "rule_list_id": "aws.ec2.launch_template.root_volume_encrypted_by_default",
      "compliance_function": "aws_ec2_launch_template_no_secrets",
      "similarity_score": 0.54,
      "match_type": "similarity",
      "rule_details": {
        "cloud_provider": "aws",
        "service": "ec2",
        "resource": "launch_template",
        "program": "compute.security.launch_template.root_volume_encrypted_by_default",
        "scope": "compute.launch_template",
        "implementation_status": "stub"
      },
      "compliance_usage": 3
    },
    {
      "rule_list_id": "aws.ec2.launch_template.instance_profile_least_privilege",
      "compliance_function": "aws_ec2_launch_template_no_public_ip",
      "similarity_score": 0.535,
      "match_type": "similarity",
      "rule_details": {
        "cloud_provider": "aws",
        "service": "ec2",
        "resource": "launch_template",
        "program": "compute.security.instance_group.instance_profile_least_privilege",
        "scope": "compute.instance_group",
        "implementation_status": "stub"
      },
      "compliance_usage": 4
    },
    {
      "rule_list_id": "aws.api_gateway.stage.api_access_log_sink_configured",
      "compliance_function": "aws_apigatewayv2_api_access_logging_enabled",
      "similarity_score": 0.53,
      "match_type": "similarity",
      "rule_details": {
        "cloud_provider": "aws",
        "service": "api_gateway",
        "resource": "stage",
        "program": "api_security.monitoring.api_access_log_sink_configured",
        "scope": "api.monitoring",
        "implementation_status": "stub"
      },
      "compliance_usage": 3
    },
    {
      "rule_list_id": "aws.api_gateway.usage_plan.api_usage_plan_required_for_api_keys",
      "compliance_function": "aws_apigateway_api_gateway_https_required",
      "similarity_score": 0.527,
      "match_type": "similarity",
      "rule_details": {
        "cloud_provider": "aws",
        "service": "api_gateway",
        "resource": "usage_plan",
        "program": "api_security.rate_limiting.api_usage_plan_required_for_api_keys",
        "scope": "api.rate_limiting",
        "implementation_status": "stub"
      },
      "compliance_usage": 2
    },
    {
      "rule_list_id": "aws.ec2.instance.data_volumes_encrypted_cmek",
      "compliance_function": "aws_ec2_instance_secrets_user_data",
      "similarity_score": 0.527,
      "match_type": "similarity",
      "rule_details": {
        "cloud_provider": "aws",
        "service": "ec2",
        "resource": "instance",
        "program": "compute.security.vm.data_volumes_encrypted_cmek",
        "scope": "compute.vm",
        "implementation_status": "stub"
      },
      "compliance_usage": 3
    },
    {
      "rule_list_id": "aws.backup.backup_plan.backup_admins_mfa_required",
      "compliance_function": "aws_backup_plan_min_retention",
      "similarity_score": 0.526,
      "match_type": "similarity",
      "rule_details": {
        "cloud_provider": "aws",
        "service": "backup",
        "resource": "backup_plan",
        "program": "backup.security.access.backup_admins_mfa_required",
        "scope": "backup.plan",
        "implementation_status": "stub"
      },
      "compliance_usage": 4
    },
    {
      "rule_list_id": "aws.backup.backup_plan.failed_jobs_alerting_enabled",
      "compliance_function": "aws_backup_plan_min_retention",
      "similarity_score": 0.522,
      "match_type": "similarity",
      "rule_details": {
        "cloud_provider": "aws",
        "service": "backup",
        "resource": "backup_plan",
        "program": "resilience_recovery.backup.health.failed_jobs_alerting_enabled",
        "scope": "backup.plan",
        "implementation_status": "stub"
      },
      "compliance_usage": 4
    },
    {
      "rule_list_id": "aws.glacier.vault.key_rotation_enabled",
      "compliance_function": "aws_iam_access_key_rotation_90_days_check",
      "similarity_score": 0.522,
      "match_type": "similarity",
      "rule_details": {
        "cloud_provider": "aws",
        "service": "glacier",
        "resource": "vault",
        "program": "backup.security.encryption.key_rotation_enabled",
        "scope": "backup.vault",
        "implementation_status": "stub"
      },
      "compliance_usage": 32
    },
    {
      "rule_list_id": "aws.api_gateway.throttle.api_usage_plan_required_for_api_keys",
      "compliance_function": "aws_apigateway_api_gateway_https_required",
      "similarity_score": 0.52,
      "match_type": "similarity",
      "rule_details": {
        "cloud_provider": "aws",
        "service": "api_gateway",
        "resource": "throttle",
        "program": "api_security.rate_limiting.api_usage_plan_required_for_api_keys",
        "scope": "api.rate_limiting",
        "implementation_status": "stub"
      },
      "compliance_usage": 2
    },
    {
      "rule_list_id": "aws.ec2.instance.serial_console_access_restricted",
      "compliance_function": "aws_iam_user_console_access_unused",
      "similarity_score": 0.517,
      "match_type": "similarity",
      "rule_details": {
        "cloud_provider": "aws",
        "service": "ec2",
        "resource": "instance",
        "program": "compute.security.vm.serial_console_access_restricted",
        "scope": "compute.vm",
        "implementation_status": "stub"
      },
      "compliance_usage": 32
    },
    {
      "rule_list_id": "aws.backup.backup_plan.no_public_access_to_backup_vault",
      "compliance_function": "aws_s3_account_level_public_access_blocks",
      "similarity_score": 0.517,
      "match_type": "similarity",
      "rule_details": {
        "cloud_provider": "aws",
        "service": "backup",
        "resource": "backup_plan",
        "program": "backup.security.access.no_public_access_to_backup_vault",
        "scope": "backup.plan",
        "implementation_status": "stub"
      },
      "compliance_usage": 72
    },
    {
      "rule_list_id": "aws.ebs.snapshot.cmk_cmek_configured",
      "compliance_function": "aws_ec2_ebs_public_snapshot",
      "similarity_score": 0.515,
      "match_type": "similarity",
      "rule_details": {
        "cloud_provider": "aws",
        "service": "ebs",
        "resource": "snapshot",
        "program": "compute.security.disk.cmk_cmek_configured",
        "scope": "compute.disk",
        "implementation_status": "stub"
      },
      "compliance_usage": 91
    },
    {
      "rule_list_id": "aws.backup.backup_plan.unprotected_assets_alerting_enabled",
      "compliance_function": "aws_backup_plan_min_retention",
      "similarity_score": 0.513,
      "match_type": "similarity",
      "rule_details": {
        "cloud_provider": "aws",
        "service": "backup",
        "resource": "backup_plan",
        "program": "resilience_recovery.backup.coverage.unprotected_assets_alerting_enabled",
        "scope": "backup.plan",
        "implementation_status": "stub"
      },
      "compliance_usage": 4
    },
    {
      "rule_list_id": "aws.cloudwatch.metric.api_access_log_fields_identity_present",
      "compliance_function": "aws_cloudwatch_log_metric_filter_unauthorized_api_calls",
      "similarity_score": 0.507,
      "match_type": "similarity",
      "rule_details": {
        "cloud_provider": "aws",
        "service": "cloudwatch",
        "resource": "metric",
        "program": "api_security.monitoring.api_access_log_fields_identity_present",
        "scope": "api.monitoring",
        "implementation_status": "stub"
      },
      "compliance_usage": 4
    },
    {
      "rule_list_id": "aws.backup.backup_plan.backup_keys_access_least_privilege",
      "compliance_function": "aws_iam_qldb_access_policy_least_privilege_audit",
      "similarity_score": 0.506,
      "match_type": "similarity",
      "rule_details": {
        "cloud_provider": "aws",
        "service": "backup",
        "resource": "backup_plan",
        "program": "backup.security.access.backup_keys_access_least_privilege",
        "scope": "backup.plan",
        "implementation_status": "stub"
      },
      "compliance_usage": 1
    },
    {
      "rule_list_id": "aws.backup.backup_plan.policy_assignment_complete",
      "compliance_function": "aws_backup_plan_min_retention",
      "similarity_score": 0.505,
      "match_type": "similarity",
      "rule_details": {
        "cloud_provider": "aws",
        "service": "backup",
        "resource": "backup_plan",
        "program": "resilience_recovery.backup.coverage.policy_assignment_complete",
        "scope": "backup.plan",
        "implementation_status": "stub"
      },
      "compliance_usage": 4
    }
  ],
  "stats": {
    "rule_list_total": 1353,
    "compliance_total": 523,
    "matched": 54,
    "coverage_pct": 5.5
  }
}