{
  "service_name": "BLOB_CONTAINER",
  "display_name": "Azure Blob_Container",
  "functions": [
    {
      "function_name": "storage_blob_container_keyvault_encryption",
      "category": "storage",
      "description": "Checks if blob containers are encrypted using Azure Key Vault for compliance and data protection.",
      "execution_type": "Code Executable",
      "remediation_effort": "Programmable",
      "compliance_frameworks": [
        "NIST Cybersecurity Framework",
        "PCI DSS v4.0",
        "ISO 27001",
        "SOC 2",
        "GDPR",
        "HIPAA",
        "Azure Security Benchmark"
      ]
    },
    {
      "function_name": "storage_offsite_assets_protected",
      "category": "storage",
      "description": "Checks if offsite assets stored in blob containers are protected according to compliance requirements.",
      "execution_type": "Code Executable",
      "remediation_effort": "Programmable",
      "compliance_frameworks": [
        "NIST Cybersecurity Framework",
        "PCI DSS v4.0",
        "ISO 27001",
        "SOC 2",
        "GDPR",
        "HIPAA",
        "Azure Security Benchmark"
      ]
    }
  ],
  "summary": {
    "total_functions": 2,
    "categories": ["storage"],
    "frameworks_covered": [
      "NIST Cybersecurity Framework",
      "PCI DSS v4.0",
      "ISO 27001",
      "SOC 2",
      "GDPR",
      "HIPAA",
      "Azure Security Benchmark"
    ]
  }
}